{
    "year": 2023,
    "month": 12,
    "dates": [
        {
            "date": "2023-12-01",
            "new_users": 0,
            "meetings": 0,
            "participants": 0,
            "meeting_minutes": 0
        },
        {
            "date": "2023-12-02",
            "new_users": 0,
            "meetings": 0,
            "participants": 0,
            "meeting_minutes": 0
        },
        {
            "date": "2023-12-03",
            "new_users": 0,
            "meetings": 0,
            "participants": 0,
            "meeting_minutes": 0
        },
        {
            "date": "2023-12-04",
            "new_users": 0,
            "meetings": 0,
            "participants": 0,
            "meeting_minutes": 0
        },
        {
            "date": "2023-12-05",
            "new_users": 0,
            "meetings": 0,
            "participants": 0,
            "meeting_minutes": 0
        },
        {
            "date": "2023-12-06",
            "new_users": 0,
            "meetings": 0,
            "participants": 0,
            "meeting_minutes": 0
        },
        {
            "date": "2023-12-07",
            "new_users": 0,
            "meetings": 0,
            "participants": 0,
            "meeting_minutes": 0
        },
        {
            "date": "2023-12-08",
            "new_users": 0,
            "meetings": 0,
            "participants": 0,
            "meeting_minutes": 0
        },
        {
            "date": "2023-12-09",
            "new_users": 0,
            "meetings": 0,
            "participants": 0,
            "meeting_minutes": 0
        },
        {
            "date": "2023-12-10",
            "new_users": 0,
            "meetings": 0,
            "participants": 0,
            "meeting_minutes": 0
        },
        {
            "date": "2023-12-11",
            "new_users": 0,
            "meetings": 0,
            "participants": 0,
            "meeting_minutes": 0
        },
        {
            "date": "2023-12-12",
            "new_users": 0,
            "meetings": 0,
            "participants": 0,
            "meeting_minutes": 0
        },
        {
            "date": "2023-12-13",
            "new_users": 0,
            "meetings": 0,
            "participants": 0,
            "meeting_minutes": 0
        },
        {
            "date": "2023-12-14",
            "new_users": 0,
            "meetings": 0,
            "participants": 0,
            "meeting_minutes": 0
        },
        {
            "date": "2023-12-15",
            "new_users": 0,
            "meetings": 0,
            "participants": 0,
            "meeting_minutes": 0
        },
        {
            "date": "2023-12-16",
            "new_users": 0,
            "meetings": 0,
            "participants": 0,
            "meeting_minutes": 0
        },
        {
            "date": "2023-12-17",
            "new_users": 0,
            "meetings": 0,
            "participants": 0,
            "meeting_minutes": 0
        },
        {
            "date": "2023-12-18",
            "new_users": 0,
            "meetings": 0,
            "participants": 0,
            "meeting_minutes": 0
        },
        {
            "date": "2023-12-19",
            "new_users": 0,
            "meetings": 0,
            "participants": 0,
            "meeting_minutes": 0
        },
        {
            "date": "2023-12-20",
            "new_users": 0,
            "meetings": 0,
            "participants": 0,
            "meeting_minutes": 0
        }
    ]
}